{"players": [{"player_slot": 0, "team_number": 0, "team_slot": 0, "hero_id": 15, "hero_variant": 1, "item_0": 147, "item_1": 50, "item_2": 116, "item_3": 139, "item_4": 160, "item_5": 154, "backpack_0": 0, "backpack_1": 0, "backpack_2": 0, "item_neutral": 949, "kills": 12, "deaths": 8, "assists": 9, "leaver_status": 0, "last_hits": 454, "denies": 13, "gold_per_min": 634, "xp_per_min": 845, "level": 26, "net_worth": 26543, "aghanims_scepter": 0, "aghanims_shard": 0, "moonshard": 0, "hero_damage": 55696, "tower_damage": 0, "hero_healing": 0, "gold": 1393, "gold_spent": 28790, "ability_upgrades_arr": [5082, 1224, 5082, 5083, 5082, 5085, 5082, 5083, 5083, 6861, 5083, 5085, 1224, 1224, 6028, 1224, 5085, 6408, 1065], "is_subscriber": false, "radiant_win": false, "start_time": 1728059836, "duration": 2981, "cluster": 272, "lobby_type": 7, "game_mode": 22, "is_contributor": false, "patch": 56, "region": 3, "isRadiant": true, "win": 0, "lose": 1, "total_gold": 31499, "total_xp": 41982, "kills_per_min": 0.24152968802415298, "kda": 2.33, "abandons": 0, "benchmarks": {"gold_per_min": {"raw": 634, "pct": 0.8544959128065395}, "xp_per_min": {"raw": 845, "pct": 0.7275204359673024}, "kills_per_min": {"raw": 0.24152968802415295, "pct": 0.5956403269754769}, "last_hits_per_min": {"raw": 9.137873196913787, "pct": 0.9602179836512261}, "hero_damage_per_min": {"raw": 1121.019792016102, "pct": 0.8920980926430517}, "hero_healing_per_min": {"raw": 0, "pct": 0.6583106267029972}, "tower_damage": {"raw": 0, "pct": 0.09100817438692098}}}, {"player_slot": 1, "team_number": 0, "team_slot": 1, "hero_id": 37, "hero_variant": 2, "item_0": 152, "item_1": 180, "item_2": 34, "item_3": 1802, "item_4": 108, "item_5": 218, "backpack_0": 0, "backpack_1": 0, "backpack_2": 0, "item_neutral": 675, "kills": 2, "deaths": 12, "assists": 15, "leaver_status": 0, "last_hits": 193, "denies": 1, "gold_per_min": 364, "xp_per_min": 504, "level": 21, "net_worth": 14812, "aghanims_scepter": 0, "aghanims_shard": 1, "moonshard": 0, "hero_damage": 82120, "tower_damage": 1485, "hero_healing": 3446, "gold": 2572, "gold_spent": 12690, "ability_upgrades_arr": [5163, 5162, 5163, 5162, 5163, 5165, 5163, 5164, 5164, 1038, 5164, 5165, 5164, 5162, 845, 5162, 5165, 6505], "is_subscriber": false, "radiant_win": false, "start_time": 1728059836, "duration": 2981, "cluster": 272, "lobby_type": 7, "game_mode": 22, "is_contributor": false, "patch": 56, "region": 3, "isRadiant": true, "win": 0, "lose": 1, "total_gold": 18084, "total_xp": 25040, "kills_per_min": 0.0402549480040255, "kda": 1.31, "abandons": 0, "benchmarks": {"gold_per_min": {"raw": 364, "pct": 0.3389168062534897}, "xp_per_min": {"raw": 504, "pct": 0.4221105527638191}, "kills_per_min": {"raw": 0.040254948004025494, "pct": 0.1328866554997208}, "last_hits_per_min": {"raw": 3.884602482388461, "pct": 0.8542713567839196}, "hero_damage_per_min": {"raw": 1652.8681650452868, "pct": 0.9994416527079844}, "hero_healing_per_min": {"raw": 69.35927541093592, "pct": 0.17420435510887772}, "tower_damage": {"raw": 1485, "pct": 0.40312674483528754}}}, {"player_slot": 2, "team_number": 0, "team_slot": 2, "hero_id": 16, "hero_variant": 1, "item_0": 1, "item_1": 108, "item_2": 180, "item_3": 119, "item_4": 0, "item_5": 0, "backpack_0": 0, "backpack_1": 0, "backpack_2": 0, "item_neutral": 300, "kills": 5, "deaths": 11, "assists": 10, "leaver_status": 0, "last_hits": 211, "denies": 7, "gold_per_min": 350, "xp_per_min": 510, "level": 21, "net_worth": 14347, "aghanims_scepter": 0, "aghanims_shard": 0, "moonshard": 0, "hero_damage": 46162, "tower_damage": 0, "hero_healing": 0, "gold": 1222, "gold_spent": 14155, "ability_upgrades_arr": [5102, 5103, 5103, 5102, 5103, 5105, 5103, 5102, 5102, 6530, 1229, 5105, 1229, 1229, 6409, 1229, 5105, 498], "is_subscriber": false, "radiant_win": false, "start_time": 1728059836, "duration": 2981, "cluster": 272, "lobby_type": 7, "game_mode": 22, "is_contributor": false, "patch": 56, "region": 3, "isRadiant": true, "win": 0, "lose": 1, "total_gold": 17389, "total_xp": 25338, "kills_per_min": 0.10063737001006375, "kda": 1.25, "abandons": 0, "benchmarks": {"gold_per_min": {"raw": 350, "pct": 0.12164429530201343}, "xp_per_min": {"raw": 510, "pct": 0.18624161073825504}, "kills_per_min": {"raw": 0.10063737001006373, "pct": 0.20302013422818793}, "last_hits_per_min": {"raw": 4.2468970144246905, "pct": 0.31208053691275167}, "hero_damage_per_min": {"raw": 929.1244548809125, "pct": 0.7533557046979866}, "hero_healing_per_min": {"raw": 0, "pct": 0.8833892617449665}, "tower_damage": {"raw": 0, "pct": 0.20218120805369127}}}, {"account_id": 338694693, "player_slot": 3, "team_number": 0, "team_slot": 3, "hero_id": 14, "hero_variant": 2, "item_0": 214, "item_1": 36, "item_2": 127, "item_3": 102, "item_4": 69, "item_5": 0, "backpack_0": 0, "backpack_1": 0, "backpack_2": 0, "item_neutral": 949, "kills": 0, "deaths": 6, "assists": 2, "leaver_status": 0, "last_hits": 62, "denies": 10, "gold_per_min": 189, "xp_per_min": 440, "level": 20, "net_worth": 8746, "aghanims_scepter": 0, "aghanims_shard": 0, "moonshard": 0, "hero_damage": 9208, "tower_damage": 0, "hero_healing": 0, "gold": 1371, "gold_spent": 7965, "ability_upgrades_arr": [5075, 5074, 5076, 5075, 5075, 5077, 5075, 5076, 5074, 5932, 5074, 5077, 5074, 730, 507, 730, 730, 5077, 332, 730], "personaname": "Neicos", "name": null, "last_login": null, "rank_tier": 13, "computed_mmr": 3949.83, "is_subscriber": false, "radiant_win": false, "start_time": 1728059836, "duration": 2981, "cluster": 272, "lobby_type": 7, "game_mode": 22, "is_contributor": false, "patch": 56, "region": 3, "isRadiant": true, "win": 0, "lose": 1, "total_gold": 9390, "total_xp": 21860, "kda": 0.29, "abandons": 0, "benchmarks": {"gold_per_min": {"raw": 189, "pct": 0.006479859894921191}, "xp_per_min": {"raw": 440, "pct": 0.1796847635726795}, "kills_per_min": {"raw": 0, "pct": 0.014535901926444834}, "last_hits_per_min": {"raw": 1.2479033881247905, "pct": 0.18178633975481612}, "hero_damage_per_min": {"raw": 185.33378061053335, "pct": 0.01838879159369527}, "hero_healing_per_min": {"raw": 0, "pct": 0.7471103327495622}, "tower_damage": {"raw": 0, "pct": 0.2597197898423818}}}, {"account_id": 1002484031, "player_slot": 4, "team_number": 0, "team_slot": 4, "hero_id": 71, "hero_variant": 1, "item_0": 73, "item_1": 116, "item_2": 0, "item_3": 50, "item_4": 249, "item_5": 1107, "backpack_0": 0, "backpack_1": 0, "backpack_2": 0, "item_neutral": 309, "kills": 9, "deaths": 10, "assists": 7, "leaver_status": 0, "last_hits": 130, "denies": 4, "gold_per_min": 343, "xp_per_min": 573, "level": 22, "net_worth": 14918, "aghanims_scepter": 0, "aghanims_shard": 0, "moonshard": 0, "hero_damage": 15434, "tower_damage": 0, "hero_healing": 125, "gold": 713, "gold_spent": 15065, "ability_upgrades_arr": [5355, 5353, 5355, 7301, 5355, 5356, 5355, 5353, 5353, 5353, 5931, 5356, 7301, 7301, 6253, 7301, 5356, 6149], "personaname": "Blacklist", "name": null, "last_login": null, "rank_tier": 45, "computed_mmr": 4231.9, "is_subscriber": false, "radiant_win": false, "start_time": 1728059836, "duration": 2981, "cluster": 272, "lobby_type": 7, "game_mode": 22, "is_contributor": false, "patch": 56, "region": 3, "isRadiant": true, "win": 0, "lose": 1, "total_gold": 17041, "total_xp": 28468, "kills_per_min": 0.18114726601811473, "kda": 1.45, "abandons": 0, "benchmarks": {"gold_per_min": {"raw": 343, "pct": 0.2570172472100101}, "xp_per_min": {"raw": 573, "pct": 0.3422387554954346}, "kills_per_min": {"raw": 0.18114726601811473, "pct": 0.5458234697328374}, "last_hits_per_min": {"raw": 2.616571620261657, "pct": 0.5454852891444031}, "hero_damage_per_min": {"raw": 310.6474337470647, "pct": 0.09807237064592493}, "hero_healing_per_min": {"raw": 2.5159342502515933, "pct": 0.7788298951640176}, "tower_damage": {"raw": 0, "pct": 0.22590463307406156}}}, {"player_slot": 128, "team_number": 1, "team_slot": 0, "hero_id": 40, "hero_variant": 1, "item_0": 931, "item_1": 267, "item_2": 36, "item_3": 4204, "item_4": 569, "item_5": 108, "backpack_0": 0, "backpack_1": 75, "backpack_2": 0, "item_neutral": 300, "kills": 8, "deaths": 13, "assists": 23, "leaver_status": 0, "last_hits": 146, "denies": 3, "gold_per_min": 436, "xp_per_min": 578, "level": 23, "net_worth": 19317, "aghanims_scepter": 0, "aghanims_shard": 1, "moonshard": 0, "hero_damage": 29146, "tower_damage": 1710, "hero_healing": 381, "gold": 4832, "gold_spent": 15140, "ability_upgrades_arr": [5178, 5179, 5178, 5179, 5178, 1105, 5180, 5179, 5178, 859, 5180, 1105, 5179, 5180, 6532, 5180, 1105, 1083], "is_subscriber": false, "radiant_win": false, "start_time": 1728059836, "duration": 2981, "cluster": 272, "lobby_type": 7, "game_mode": 22, "is_contributor": false, "patch": 56, "region": 3, "isRadiant": false, "win": 1, "lose": 0, "total_gold": 21661, "total_xp": 28716, "kills_per_min": 0.161019792016102, "kda": 2.21, "abandons": 0, "benchmarks": {"gold_per_min": {"raw": 436, "pct": 0.710068875040997}, "xp_per_min": {"raw": 578, "pct": 0.5529681862905871}, "kills_per_min": {"raw": 0.16101979201610198, "pct": 0.6808789767136766}, "last_hits_per_min": {"raw": 2.9386112042938612, "pct": 0.5985569039029189}, "hero_damage_per_min": {"raw": 586.6353572626635, "pct": 0.3938996392259757}, "hero_healing_per_min": {"raw": 7.668567594766857, "pct": 0.458510987208921}, "tower_damage": {"raw": 1710, "pct": 0.6903902918989833}}}, {"account_id": 112681997, "player_slot": 129, "team_number": 1, "team_slot": 1, "hero_id": 82, "hero_variant": 1, "item_0": 1, "item_1": 160, "item_2": 1097, "item_3": 96, "item_4": 108, "item_5": 63, "backpack_0": 16, "backpack_1": 0, "backpack_2": 0, "item_neutral": 239, "kills": 24, "deaths": 2, "assists": 11, "leaver_status": 0, "last_hits": 456, "denies": 6, "gold_per_min": 768, "xp_per_min": 1244, "level": 29, "net_worth": 37481, "aghanims_scepter": 0, "aghanims_shard": 1, "moonshard": 0, "hero_damage": 35013, "tower_damage": 15606, "hero_healing": 0, "gold": 11481, "gold_spent": 27095, "additional_units": [{"unitname": "", "item_0": 1, "item_1": 160, "item_2": 1097, "item_3": 96, "item_4": 108, "item_5": 63, "backpack_0": 16, "backpack_1": 0, "backpack_2": 0, "item_neutral": 0}], "ability_upgrades_arr": [5430, 5431, 5433, 7318, 5431, 5431, 5431, 7318, 7318, 5433, 6689, 7318, 5430, 5430, 5430, 5972, 5433, 7102, 5433, 6195, 6115, 7027, 618], "personaname": "Seeerb", "name": null, "last_login": "2025-09-03T17:35:27.072Z", "rank_tier": 24, "computed_mmr": null, "is_subscriber": false, "radiant_win": false, "start_time": 1728059836, "duration": 2981, "cluster": 272, "lobby_type": 7, "game_mode": 22, "is_contributor": false, "patch": 56, "region": 3, "isRadiant": false, "win": 1, "lose": 0, "total_gold": 38156, "total_xp": 61806, "kills_per_min": 0.48305937604830596, "kda": 11.67, "abandons": 0, "benchmarks": {"gold_per_min": {"raw": 768, "pct": 0.8335170893054025}, "xp_per_min": {"raw": 1244, "pct": 0.9636163175303197}, "kills_per_min": {"raw": 0.4830593760483059, "pct": 0.9128996692392503}, "last_hits_per_min": {"raw": 9.178128144917812, "pct": 0.6306504961411246}, "hero_damage_per_min": {"raw": 704.7232472324723, "pct": 0.7089305402425579}, "hero_healing_per_min": {"raw": 0, "pct": 0.9779492833517089}, "tower_damage": {"raw": 15606, "pct": 0.8721058434399118}}}, {"player_slot": 130, "team_number": 1, "team_slot": 2, "hero_id": 42, "hero_variant": 2, "item_0": 114, "item_1": 127, "item_2": 50, "item_3": 151, "item_4": 137, "item_5": 218, "backpack_0": 0, "backpack_1": 0, "backpack_2": 0, "item_neutral": 1156, "kills": 5, "deaths": 5, "assists": 15, "leaver_status": 0, "last_hits": 151, "denies": 5, "gold_per_min": 401, "xp_per_min": 616, "level": 23, "net_worth": 18575, "aghanims_scepter": 0, "aghanims_shard": 1, "moonshard": 0, "hero_damage": 17139, "tower_damage": 5527, "hero_healing": 0, "gold": 925, "gold_spent": 18690, "ability_upgrades_arr": [5086, 5088, 1282, 5088, 5088, 5089, 5088, 1282, 1282, 1282, 5086, 5089, 5086, 5086, 6088, 5976, 5089, 6444], "is_subscriber": false, "radiant_win": false, "start_time": 1728059836, "duration": 2981, "cluster": 272, "lobby_type": 7, "game_mode": 22, "is_contributor": false, "patch": 56, "region": 3, "isRadiant": false, "win": 1, "lose": 0, "total_gold": 19923, "total_xp": 30604, "kills_per_min": 0.10063737001006375, "kda": 3.33, "abandons": 0, "benchmarks": {"gold_per_min": {"raw": 401, "pct": 0.10826844642195031}, "xp_per_min": {"raw": 616, "pct": 0.2039302929180571}, "kills_per_min": {"raw": 0.10063737001006373, "pct": 0.1553578049684835}, "last_hits_per_min": {"raw": 3.039248574303925, "pct": 0.05079718205413422}, "hero_damage_per_min": {"raw": 344.9647769204965, "pct": 0.06414534668149796}, "hero_healing_per_min": {"raw": 0, "pct": 0.9484612532443456}, "tower_damage": {"raw": 5527, "pct": 0.45383759733036705}}}, {"player_slot": 131, "team_number": 1, "team_slot": 3, "hero_id": 94, "hero_variant": 3, "item_0": 123, "item_1": 141, "item_2": 250, "item_3": 108, "item_4": 63, "item_5": 0, "backpack_0": 0, "backpack_1": 0, "backpack_2": 0, "item_neutral": 1160, "kills": 2, "deaths": 6, "assists": 25, "leaver_status": 0, "last_hits": 332, "denies": 4, "gold_per_min": 543, "xp_per_min": 785, "level": 26, "net_worth": 26759, "aghanims_scepter": 0, "aghanims_shard": 1, "moonshard": 0, "hero_damage": 18990, "tower_damage": 5931, "hero_healing": 0, "gold": 3234, "gold_spent": 23525, "ability_upgrades_arr": [5505, 5504, 5505, 5504, 1475, 5507, 5505, 5504, 5504, 1345, 5505, 5507, 1475, 1475, 6392, 1475, 5507, 6182, 6803], "is_subscriber": false, "radiant_win": false, "start_time": 1728059836, "duration": 2981, "cluster": 272, "lobby_type": 7, "game_mode": 22, "is_contributor": false, "patch": 56, "region": 3, "isRadiant": false, "win": 1, "lose": 0, "total_gold": 26978, "total_xp": 39001, "kills_per_min": 0.0402549480040255, "kda": 3.86, "abandons": 0, "benchmarks": {"gold_per_min": {"raw": 543, "pct": 0.33263598326359833}, "xp_per_min": {"raw": 785, "pct": 0.4131799163179916}, "kills_per_min": {"raw": 0.040254948004025494, "pct": 0.11192468619246862}, "last_hits_per_min": {"raw": 6.682321368668232, "pct": 0.18828451882845187}, "hero_damage_per_min": {"raw": 382.22073129822206, "pct": 0.1799163179916318}, "hero_healing_per_min": {"raw": 0, "pct": 0.952928870292887}, "tower_damage": {"raw": 5931, "pct": 0.5209205020920502}}}, {"player_slot": 132, "team_number": 1, "team_slot": 4, "hero_id": 67, "hero_variant": 2, "item_0": 63, "item_1": 127, "item_2": 160, "item_3": 137, "item_4": 114, "item_5": 139, "backpack_0": 0, "backpack_1": 0, "backpack_2": 0, "item_neutral": 1156, "kills": 7, "deaths": 5, "assists": 23, "leaver_status": 0, "last_hits": 338, "denies": 16, "gold_per_min": 615, "xp_per_min": 979, "level": 27, "net_worth": 30467, "aghanims_scepter": 0, "aghanims_shard": 1, "moonshard": 0, "hero_damage": 31572, "tower_damage": 6010, "hero_healing": 0, "gold": 4517, "gold_spent": 26215, "ability_upgrades_arr": [5334, 5336, 5336, 5334, 5335, 7851, 5336, 5336, 5334, 5335, 5334, 7851, 5335, 5335, 5910, 8040, 7851, 6195, 6903, 6148], "is_subscriber": false, "radiant_win": false, "start_time": 1728059836, "duration": 2981, "cluster": 272, "lobby_type": 7, "game_mode": 22, "is_contributor": false, "patch": 56, "region": 3, "isRadiant": false, "win": 1, "lose": 0, "total_gold": 30555, "total_xp": 48639, "kills_per_min": 0.14089231801408925, "kda": 5, "abandons": 0, "benchmarks": {"gold_per_min": {"raw": 615, "pct": 0.5659090909090909}, "xp_per_min": {"raw": 979, "pct": 0.6416666666666667}, "kills_per_min": {"raw": 0.14089231801408922, "pct": 0.17954545454545454}, "last_hits_per_min": {"raw": 6.803086212680308, "pct": 0.5522727272727272}, "hero_damage_per_min": {"raw": 635.4646091915465, "pct": 0.18333333333333332}, "hero_healing_per_min": {"raw": 0, "pct": 0.956060606060606}, "tower_damage": {"raw": 6010, "pct": 0.6674242424242425}}}], "radiant_win": false, "duration": 2981, "pre_game_duration": 90, "start_time": 1728059836, "match_id": 7972777689, "match_seq_num": 6707110326, "tower_status_radiant": 0, "tower_status_dire": 1974, "barracks_status_radiant": 0, "barracks_status_dire": 63, "cluster": 272, "first_blood_time": 0, "lobby_type": 7, "human_players": 10, "leagueid": 0, "game_mode": 22, "flags": 1, "engine": 1, "radiant_score": 31, "dire_score": 47, "picks_bans": [{"is_pick": true, "hero_id": 14, "team": 0, "order": 0}, {"is_pick": true, "hero_id": 37, "team": 0, "order": 1}, {"is_pick": true, "hero_id": 40, "team": 1, "order": 2}, {"is_pick": true, "hero_id": 67, "team": 1, "order": 3}, {"is_pick": true, "hero_id": 71, "team": 0, "order": 4}, {"is_pick": true, "hero_id": 15, "team": 0, "order": 5}, {"is_pick": true, "hero_id": 82, "team": 1, "order": 6}, {"is_pick": true, "hero_id": 42, "team": 1, "order": 7}, {"is_pick": true, "hero_id": 16, "team": 0, "order": 8}, {"is_pick": true, "hero_id": 94, "team": 1, "order": 9}, {"is_pick": false, "hero_id": 56, "team": 0, "order": 10}, {"is_pick": false, "hero_id": 35, "team": 0, "order": 11}, {"is_pick": false, "hero_id": 76, "team": 0, "order": 12}, {"is_pick": false, "hero_id": 99, "team": 0, "order": 13}, {"is_pick": false, "hero_id": 10, "team": 0, "order": 14}], "od_data": {"has_api": true, "has_gcdata": false, "has_parsed": false, "has_archive": false}, "metadata": null, "patch": 56, "region": 3}